click_demo/__init__.py
click_demo/cli.py
click_demo/click_demo.py
click_demo-0.1.0.dist-info/AUTHORS.rst
click_demo-0.1.0.dist-info/LICENSE
click_demo-0.1.0.dist-info/METADATA
click_demo-0.1.0.dist-info/WHEEL
click_demo-0.1.0.dist-info/entry_points.txt
click_demo-0.1.0.dist-info/top_level.txt
click_demo-0.1.0.dist-info/RECORD
