Metadata-Version: 2.1
Name: click-demo
Version: 0.1.0
Summary: Simple click greeting commands, Hi and Bye only :)
Home-page: https://github.com/parashuram-patil/click_demo
Author: Parashuram S. Patil
Author-email: parasharam_patil@ymail.com
License: MIT license
Keywords: click_demo
Platform: UNKNOWN
Classifier: Development Status :: 2 - Pre-Alpha
Classifier: Intended Audience :: Developers
Classifier: License :: OSI Approved :: MIT License
Classifier: Natural Language :: English
Classifier: Programming Language :: Python :: 2
Classifier: Programming Language :: Python :: 2.7
Classifier: Programming Language :: Python :: 3
Classifier: Programming Language :: Python :: 3.4
Classifier: Programming Language :: Python :: 3.5
Classifier: Programming Language :: Python :: 3.6
Classifier: Programming Language :: Python :: 3.7
Requires-Dist: Click (>=7.0)
